{"name":"Environaut\\Config\\IConfigHandler","line":9,"short_desc":"Default interface all Environaut config handlers must implement.","long_desc":"","hint":null,"tags":[],"namespace":"Environaut\\Config","file":"\/home\/graste\/projects\/environaut\/src\/Environaut\/Config\/IConfigHandler.php","hash":"6a5c30e2bba5f7072a25704ff7f15fa7de171f40","parent":null,"modifiers":null,"is_trait":false,"is_interface":true,"aliases":[],"errors":[],"interfaces":[],"properties":[],"methods":{"getConfig":{"name":"getConfig","line":17,"short_desc":"Returns the currently (read and merged) config data as a concrete IConfig implementating class.","long_desc":"","hint":[["Environaut\\Config\\IConfig",false]],"hint_desc":"","tags":[],"modifiers":"1","is_by_ref":"","exceptions":[],"errors":[],"parameters":[]},"addLocation":{"name":"addLocation","line":26,"short_desc":"Adds the given location to the set of locations to check for configs.","long_desc":"","hint":null,"hint_desc":null,"tags":[],"modifiers":"1","is_by_ref":"","exceptions":[["\\InvalidArgumentException","if given location is not readable"]],"errors":[],"parameters":{"location":{"name":"location","line":26,"short_desc":"location to check for config files (usually a file\/directory path)","long_desc":null,"hint":[["mixed",false]],"tags":[],"modifiers":"","default":null,"is_by_ref":false}}},"setLocations":{"name":"setLocations","line":33,"short_desc":"Set the locations to check for config files.","long_desc":"","hint":null,"hint_desc":null,"tags":[],"modifiers":"1","is_by_ref":"","exceptions":[],"errors":[],"parameters":{"locations":{"name":"locations","line":33,"short_desc":"set of locations (usually file\/directory paths)","long_desc":null,"hint":[["array",false]],"tags":[],"modifiers":"array","default":null,"is_by_ref":false}}},"getLocations":{"name":"getLocations","line":38,"short_desc":"","long_desc":"","hint":[["array",false]],"hint_desc":"of locations used for config file lookups","tags":[],"modifiers":"1","is_by_ref":"","exceptions":[],"errors":[],"parameters":[]}},"constants":[]}